borg_encryption/__init__.py
borg_encryption/adaptive_defense.py
borg_encryption/api.py
borg_encryption/borg_encryption.py
borg_encryption/cli.py
borg_encryption/client.py
borg_encryption/key_manager.py
borg_encryption-1.0.0.dist-info/licenses/LICENSE
borg_encryption-1.0.0.dist-info/METADATA
borg_encryption-1.0.0.dist-info/WHEEL
borg_encryption-1.0.0.dist-info/entry_points.txt
borg_encryption-1.0.0.dist-info/top_level.txt
borg_encryption-1.0.0.dist-info/RECORD
