Metadata-Version: 2.4
Name: borg-encryption
Version: 1.0.0
Summary: Borg Encryption System - A multi-layered, adaptive encryption system
Author-email: Borg Collective <resistance.is.futile@borg-collective.com>
License: MIT
Project-URL: Homepage, https://github.com/borg-collective/borg-encryption
Project-URL: Bug Tracker, https://github.com/borg-collective/borg-encryption/issues
Keywords: encryption,security,cryptography,api
Classifier: Development Status :: 4 - Beta
Classifier: Intended Audience :: Developers
Classifier: License :: OSI Approved :: MIT License
Classifier: Programming Language :: Python :: 3
Classifier: Programming Language :: Python :: 3.8
Classifier: Programming Language :: Python :: 3.9
Classifier: Programming Language :: Python :: 3.10
Classifier: Programming Language :: Python :: 3.11
Classifier: Topic :: Security :: Cryptography
Requires-Python: >=3.8
License-File: LICENSE
Requires-Dist: cryptography>=41.0.0
Requires-Dist: pycryptodome>=3.19.0
Requires-Dist: pynacl>=1.5.0
Requires-Dist: fastapi>=0.104.0
Requires-Dist: uvicorn>=0.23.2
Requires-Dist: pydantic>=2.4.2
Requires-Dist: python-multipart>=0.0.6
Requires-Dist: click>=8.1.7
Requires-Dist: requests>=2.31.0
Dynamic: license-file
